cartinese/__init__.py
cartinese-0.3.0.dist-info/METADATA
cartinese-0.3.0.dist-info/WHEEL
cartinese-0.3.0.dist-info/top_level.txt
cartinese-0.3.0.dist-info/RECORD
