Metadata-Version: 2.4
Name: cartinese
Version: 0.3.0
Summary: Translate normal text into Cartinese.
Requires-Python: >=3.13
